BubbleMath/BubbleMath.py
BubbleMath/__init__.py
BubbleMath-0.0.4.dist-info/LICENSE
BubbleMath-0.0.4.dist-info/METADATA
BubbleMath-0.0.4.dist-info/WHEEL
BubbleMath-0.0.4.dist-info/top_level.txt
BubbleMath-0.0.4.dist-info/RECORD
