Metadata-Version: 2.1
Name: BubbleMath
Version: 0.0.4
Summary: UNKNOWN
Home-page: UNKNOWN
Author: SoapDoesCode
Author-email: 
License: UNKNOWN
Keywords: python,math,calculations,calculator,bubble math
Platform: UNKNOWN
Classifier: Development Status :: 1 - Planning
Classifier: Intended Audience :: Developers
Classifier: Programming Language :: Python :: 3
Classifier: Operating System :: Unix
Classifier: Operating System :: MacOS :: MacOS X
Classifier: Operating System :: Microsoft :: Windows
License-File: LICENSE
Requires-Dist: gmpy2
